thermistor_utils/Beta_converter.py
thermistor_utils/SH_converter.py
thermistor_utils/__init__.py
thermistor_utils-0.0.4.dist-info/LICENSE
thermistor_utils-0.0.4.dist-info/METADATA
thermistor_utils-0.0.4.dist-info/WHEEL
thermistor_utils-0.0.4.dist-info/top_level.txt
thermistor_utils-0.0.4.dist-info/RECORD
