Metadata-Version: 2.1
Name: thermistor-utils
Version: 0.0.4
Summary: Steinhart -- Hart and Beta thermistor temperature model in Python and C. Implementation and utilities
Home-page: https://gitlab.com/geusebi/thermistor-utils
Author: Giampaolo Eusebi
Author-email: giampaolo.eusebi@gmail.com
License: GNU LGPL 3.0
Platform: UNKNOWN
Classifier: Development Status :: 4 - Beta
Classifier: Intended Audience :: Developers
Classifier: Intended Audience :: Manufacturing
Classifier: Intended Audience :: Science/Research
Classifier: License :: OSI Approved
Classifier: License :: OSI Approved :: GNU Lesser General Public License v3 (LGPLv3)
Classifier: Operating System :: OS Independent
Classifier: Programming Language :: C
Classifier: Programming Language :: Python :: 3
Classifier: Programming Language :: Python :: 3.6
Classifier: Programming Language :: Python :: 3.7
Classifier: Topic :: Scientific/Engineering
Classifier: Topic :: Software Development :: Embedded Systems
Classifier: Topic :: Utilities
Requires-Python: >=3.6
